[
  {
    "code": "001",
    "name": "视图",
    "id": 1,
    "type": "1"
  },
  {
    "code": "001000",
    "name": "自定义视图",
    "id": 2,
    "type": "1"
  },
  {
    "code": "001001",
    "name": "多表头",
    "id": 5106180070533632,
    "type": "1"
  },
  {
    "code": "002",
    "name": "引用",
    "id": 2,
    "type": "2"
  },
  {
    "code": "002001",
    "name": "列类型",
    "id": 20,
    "type": "2"
  },
  {
    "code": "002002",
    "name": "关系类型",
    "id": 40,
    "type": "2"
  },
  {
    "code": "002003",
    "name": "约束处理类型",
    "id": 45,
    "type": "2"
  },
  {
    "code": "002004",
    "name": "分组类型",
    "id": 60,
    "type": "2"
  },
  {
    "code": "002005",
    "name": "排序类型",
    "id": 65,
    "type": "2"
  },
  {
    "code": "002006",
    "name": "控件类型",
    "id": 70,
    "type": "2"
  },
  {
    "code": "002007",
    "name": "标题位置",
    "id": 75,
    "type": "2"
  },
  {
    "code": "002008",
    "name": "显示方式",
    "id": 80,
    "type": "2"
  },
  {
    "code": "002009",
    "name": "树字段类型",
    "id": 90,
    "type": "2"
  },
  {
    "code": "002010",
    "name": "表操作类型",
    "id": 95,
    "type": "2"
  },
  {
    "code": "002011",
    "name": "界面初始化状态",
    "id": 100,
    "type": "2"
  },
  {
    "code": "002012",
    "name": "资源类型",
    "id": 4995653089241600,
    "type": "2"
  },
  {
    "code": "002013",
    "name": "界面布局类型",
    "id": 101,
    "type": "2"
  },
  {
    "code": "002014",
    "name": "用户状态",
    "id": 5106007818291712,
    "type": "2"
  },
  {
    "code": "002015",
    "name": "显示级次",
    "id": 5110934474181120,
    "type": "2"
  },
  {
    "code": "002016",
    "name": "查询扩展类型",
    "id": 5110965080951296,
    "type": "2"
  },
  {
    "code": "002017",
    "name": "显示明细类型",
    "id": 5110970820012544,
    "type": "2"
  },
  {
    "code": "002018",
    "name": "方案",
    "id": 85,
    "type": "2"
  },
  {
    "code": "002019",
    "name": "数据表",
    "id": 50,
    "type": "2"
  },
  {
    "code": "002020",
    "name": "数据源",
    "id": 25,
    "type": "2"
  },
  {
    "code": "002021",
    "name": "引用源",
    "id": 30,
    "type": "2"
  },
  {
    "code": "002022",
    "name": "页面",
    "id": 4985120922782208,
    "type": "2"
  },
  {
    "code": "002023",
    "name": "单位信息",
    "id": 4987434837756416,
    "type": "2"
  },
  {
    "code": "002024",
    "name": "视图",
    "id": 4989338214607360,
    "type": "2"
  },
  {
    "code": "002025",
    "name": "角色",
    "id": 4997069447571968,
    "type": "2"
  },
  {
    "code": "002026",
    "name": "菜单",
    "id": 4997069447571969,
    "type": "2"
  },
  {
    "code": "002027",
    "name": "操作(按钮)",
    "id": 4997069447571970,
    "type": "2"
  },
  {
    "code": "002028",
    "name": "权限资源",
    "id": 5000520889870860,
    "type": "2"
  },
  {
    "code": "002029",
    "name": "业务流程",
    "id": 5044605340658176,
    "type": "2"
  },
  {
    "code": "003",
    "name": "页面",
    "id": 3,
    "type": "3"
  }
]